{
  "cli": {
    "version": ">= 14.0.0",
    "appVersionSource": "remote"
  },
  "build": {
    "development": {
      "developmentClient": true,
      "distribution": "internal",
      "android": {
        "gradleCommand": ":app:assembleDebug",
        "buildType": "apk"
      },
      "ios": {
        "buildConfiguration": "Debug",
        "simulator": true
      }
    },
    "preview": {
      "distribution": "internal",
      "android": {
        "buildType": "apk"
      },
      "ios": {
        "simulator": false,
        "buildConfiguration": "Release"
      }
    },
    "production": {
      "android": {
        "buildType": "app-bundle"
      },
      "ios": {
        "buildConfiguration": "Release"
      }
    }
  },
  "submit": {
    "production": {
      "android": {
        "serviceAccountKeyPath": "./google-service-account.json",
        "track": "internal"
      },
      "ios": {
        "appleId": "your-apple-id@example.com",
        "ascAppId": "your-asc-app-id",
        "appleTeamId": "your-team-id"
      }
    }
  }
}
